[
  {
    "id": 1,
    "timestamp": "7/9/2022 15:23:40",
    "title": "titulo test desde pudsdst ",
    "price": 99,
    "thumbnail": "fot334343o",
    "description": "descr4343ipcion",
    "code": "OF00FD",
    "stock": 3
  },
  {
    "id": 2,
    "timestamp": "7/9/2022 15:24:10",
    "title": "titulo test desde pudsdst ",
    "price": 99,
    "thumbnail": "fot334343o",
    "description": "descr4343ipcion",
    "code": "OF00FD",
    "stock": 3
  },
  {
    "id": 3,
    "timestamp": "7/9/2022 15:59:31",
    "title": "titulo test desde pufdfdfdt ",
    "price": 99,
    "thumbnail": "fot334jreeeeeee343o",
    "description": "descr4343ipcion",
    "code": "OF00FD",
    "stock": 3
  }
]